odoo/addons/sale_order_ordered_weight/README.rst
odoo/addons/sale_order_ordered_weight/__init__.py
odoo/addons/sale_order_ordered_weight/__manifest__.py
odoo/addons/sale_order_ordered_weight/pre_init_hook.py
odoo/addons/sale_order_ordered_weight/i18n/es.po
odoo/addons/sale_order_ordered_weight/i18n/fr.po
odoo/addons/sale_order_ordered_weight/i18n/pt.po
odoo/addons/sale_order_ordered_weight/i18n/sale_order_ordered_weight.pot
odoo/addons/sale_order_ordered_weight/migrations/16.0.1.0.0/pre-migration.py
odoo/addons/sale_order_ordered_weight/models/__init__.py
odoo/addons/sale_order_ordered_weight/models/res_company.py
odoo/addons/sale_order_ordered_weight/models/res_config_settings.py
odoo/addons/sale_order_ordered_weight/models/sale_order.py
odoo/addons/sale_order_ordered_weight/models/sale_order_line.py
odoo/addons/sale_order_ordered_weight/readme/CONFIGURE.rst
odoo/addons/sale_order_ordered_weight/readme/CONTRIBUTORS.rst
odoo/addons/sale_order_ordered_weight/readme/DESCRIPTION.rst
odoo/addons/sale_order_ordered_weight/readme/USAGE.rst
odoo/addons/sale_order_ordered_weight/reports/report_sale_order.xml
odoo/addons/sale_order_ordered_weight/static/description/configuration.png
odoo/addons/sale_order_ordered_weight/static/description/icon.png
odoo/addons/sale_order_ordered_weight/static/description/index.html
odoo/addons/sale_order_ordered_weight/static/description/sale_order_form.png
odoo/addons/sale_order_ordered_weight/static/description/sale_order_report.png
odoo/addons/sale_order_ordered_weight/tests/__init__.py
odoo/addons/sale_order_ordered_weight/tests/test_sale_order_ordered_weight.py
odoo/addons/sale_order_ordered_weight/views/res_config_settings_view.xml
odoo/addons/sale_order_ordered_weight/views/sale_order_view.xml
odoo_addon_sale_order_ordered_weight-16.0.1.0.0.2.dist-info/METADATA
odoo_addon_sale_order_ordered_weight-16.0.1.0.0.2.dist-info/WHEEL
odoo_addon_sale_order_ordered_weight-16.0.1.0.0.2.dist-info/top_level.txt
odoo_addon_sale_order_ordered_weight-16.0.1.0.0.2.dist-info/RECORD
